stateforward/__init__.py
stateforward/core/__init__.py
stateforward/core/decorators.py
stateforward/core/elements.py
stateforward/core/functional.py
stateforward/model/__init__.py
stateforward/model/association.py
stateforward/model/attribute.py
stateforward/model/collection.py
stateforward/model/decorators.py
stateforward/model/element.py
stateforward/model/model.py
stateforward/model/preprocessor.py
stateforward/model/validator.py
stateforward/model/visitor.py
stateforward/protocols/__init__.py
stateforward/protocols/clock.py
stateforward/protocols/future.py
stateforward/protocols/interpreter.py
stateforward/protocols/logger.py
stateforward/protocols/queue.py
stateforward/state_machine/__init__.py
stateforward/state_machine/clocks/__init__.py
stateforward/state_machine/clocks/clock.py
stateforward/state_machine/compiler/__init__.py
stateforward/state_machine/compiler/state_machine_compiler.py
stateforward/state_machine/elements.py
stateforward/state_machine/functional.py
stateforward/state_machine/generators/__init__.py
stateforward/state_machine/generators/cursor.py
stateforward/state_machine/generators/graphviz/__init__.py
stateforward/state_machine/generators/plantuml/__init__.py
stateforward/state_machine/generators/plantuml/plantuml_generator.py
stateforward/state_machine/generators/unittest/__init__.py
stateforward/state_machine/generators/unittest/unittest_generator.py
stateforward/state_machine/interpreters/__init__.py
stateforward/state_machine/interpreters/asynchronous/__init__.py
stateforward/state_machine/interpreters/asynchronous/async_behavior_interpreter.py
stateforward/state_machine/interpreters/asynchronous/async_interpreter.py
stateforward/state_machine/interpreters/asynchronous/async_state_machine_interpreter.py
stateforward/state_machine/log.py
stateforward/state_machine/preprocessor.py
stateforward/state_machine/validator.py
stateforward-0.2.95.dist-info/LICENSE
stateforward-0.2.95.dist-info/METADATA
stateforward-0.2.95.dist-info/WHEEL
stateforward-0.2.95.dist-info/RECORD
