Metadata-Version: 2.1
Name: stateforward
Version: 0.2.95
Summary: 
Author: Gabriel Willen
Author-email: gabewillen@gmail.com
Requires-Python: >=3.10,<4.0
Classifier: Programming Language :: Python :: 3
Classifier: Programming Language :: Python :: 3.10
Classifier: Programming Language :: Python :: 3.11
Classifier: Programming Language :: Python :: 3.12
